{
  "_class": "symbolInstance",
  "booleanOperation": 0,
  "clippingMaskMode": 0,
  "do_objectID": "F3253B67-6199-43A3-9D26-F791F5AC2B02",
  "exportOptions": {
    "_class": "exportOptions",
    "exportFormats": [
    ],
    "includedLayerIds": [
    ],
    "layerOptions": 0,
    "shouldTrim": false
  },
  "frame": {
    "_class": "rect",
    "constrainProportions": false,
    "height": 16,
    "width": 312,
    "x": 16,
    "y": 59
  },
  "hasClippingMask": false,
  "horizontalSpacing": 0,
  "isFixedToViewport": false,
  "isFlippedHorizontal": false,
  "isFlippedVertical": false,
  "isLocked": false,
  "isVisible": true,
  "layerListExpandedType": 0,
  "name": "CAPTION TEXT COLOR & STYLE",
  "nameIsFixed": true,
  "overrideValues": [
    {
      "_class": "overrideValue",
      "overrideName": "6204EA1A-6F42-4991-8748-D1B87479FF2F_stringValue",
      "value": "Assistive text"
    }
  ],
  "resizingConstraint": 10,
  "resizingType": 0,
  "rotation": 0,
  "scale": 1,
  "shouldBreakMaskChain": true,
  "style": {
    "_class": "style",
    "blur": {
      "_class": "blur",
      "center": "{0.5, 0.5}",
      "isEnabled": false,
      "motionAngle": 0,
      "radius": 10,
      "saturation": 1,
      "type": 0
    },
    "borderOptions": {
      "_class": "borderOptions",
      "dashPattern": [
      ],
      "isEnabled": true,
      "lineCapStyle": 0,
      "lineJoinStyle": 0
    },
    "borders": [
    ],
    "colorControls": {
      "_class": "colorControls",
      "brightness": 0,
      "contrast": 1,
      "hue": 0,
      "isEnabled": false,
      "saturation": 1
    },
    "contextSettings": {
      "_class": "graphicsContextSettings",
      "blendMode": 0,
      "opacity": 1
    },
    "do_objectID": "99C67BD4-2A7C-4019-956A-7EB107F6E733",
    "endMarkerType": 0,
    "fills": [
    ],
    "innerShadows": [
    ],
    "miterLimit": 10,
    "shadows": [
    ],
    "startMarkerType": 0,
    "windingRule": 1
  },
  "symbolID": "E77CE76F-B955-41B3-8032-E0E938CBEB1D",
  "verticalSpacing": 0
}