{
  "_class": "symbolMaster",
  "allowsOverrides": true,
  "backgroundColor": {
    "_class": "color",
    "alpha": 1,
    "blue": 0.8980392156862745,
    "green": 0.8980392156862745,
    "red": 0.8980392156862745
  },
  "booleanOperation": 0,
  "changeIdentifier": 12596,
  "clippingMaskMode": 0,
  "do_objectID": "D2885A05-FD20-4C28-AC1A-7CAB029DD081",
  "exportOptions": {
    "_class": "exportOptions",
    "exportFormats": [
    ],
    "includedLayerIds": [
    ],
    "layerOptions": 0,
    "shouldTrim": false
  },
  "frame": {
    "_class": "rect",
    "constrainProportions": false,
    "height": 48,
    "width": 48,
    "x": 12924,
    "y": 704
  },
  "grid": {
    "_class": "simpleGrid",
    "gridSize": 4,
    "isEnabled": true,
    "thickGridTimes": 40
  },
  "groupLayout": {
    "_class": "MSImmutableFreeformGroupLayout"
  },
  "hasBackgroundColor": false,
  "hasClickThrough": true,
  "hasClippingMask": false,
  "horizontalRulerData": {
    "_class": "rulerData",
    "base": 0,
    "guides": [
    ]
  },
  "includeBackgroundColorInExport": false,
  "includeBackgroundColorInInstance": false,
  "includeInCloudUpload": true,
  "isFixedToViewport": false,
  "isFlippedHorizontal": false,
  "isFlippedVertical": false,
  "isFlowHome": false,
  "isLocked": false,
  "isVisible": true,
  "layerListExpandedType": 1,
  "layers": [
    {
      "class": "rectangle",
      "id": "DF89D7A9-B8FD-4C78-8870-6CA428159BC4"
    },
    {
      "class": "symbolInstance",
      "id": "7D9573F6-1DF5-4E6C-811E-83B78F422B8F"
    },
    {
      "class": "symbolInstance",
      "id": "7608E371-B44D-4BEA-A9C2-ABFB03597CF1"
    }
  ],
  "layout": {
    "_class": "layoutGrid",
    "columnWidth": 48,
    "drawHorizontal": true,
    "drawHorizontalLines": false,
    "drawVertical": false,
    "gutterHeight": 4,
    "gutterWidth": 2904,
    "guttersOutside": false,
    "horizontalOffset": -123,
    "isEnabled": false,
    "numberOfColumns": 2,
    "rowHeightMultiplication": 1,
    "totalWidth": 3000
  },
  "name": "Buttons / Toggle / Elements / Middle / Enabled",
  "nameIsFixed": true,
  "overrideProperties": [
    {
      "_class": "MSImmutableOverrideProperty",
      "canOverride": true,
      "overrideName": "DF89D7A9-B8FD-4C78-8870-6CA428159BC4_image"
    },
    {
      "_class": "MSImmutableOverrideProperty",
      "canOverride": true,
      "overrideName": "DF89D7A9-B8FD-4C78-8870-6CA428159BC4_layerStyle"
    },
    {
      "_class": "MSImmutableOverrideProperty",
      "canOverride": false,
      "overrideName": "7D9573F6-1DF5-4E6C-811E-83B78F422B8F_symbolID"
    },
    {
      "_class": "MSImmutableOverrideProperty",
      "canOverride": true,
      "overrideName": "7608E371-B44D-4BEA-A9C2-ABFB03597CF1_symbolID"
    }
  ],
  "presetDictionary": {
  },
  "resizesContent": true,
  "resizingConstraint": 63,
  "resizingType": 0,
  "rotation": 0,
  "shouldBreakMaskChain": true,
  "style": {
    "_class": "style",
    "blur": {
      "_class": "blur",
      "center": "{0.5, 0.5}",
      "isEnabled": false,
      "motionAngle": 0,
      "radius": 10,
      "saturation": 1,
      "type": 0
    },
    "borderOptions": {
      "_class": "borderOptions",
      "dashPattern": [
      ],
      "isEnabled": true,
      "lineCapStyle": 0,
      "lineJoinStyle": 0
    },
    "borders": [
    ],
    "colorControls": {
      "_class": "colorControls",
      "brightness": 0,
      "contrast": 1,
      "hue": 0,
      "isEnabled": false,
      "saturation": 1
    },
    "contextSettings": {
      "_class": "graphicsContextSettings",
      "blendMode": 0,
      "opacity": 1
    },
    "do_objectID": "A916FD4A-3EAB-460F-9157-21FF9CD5B619",
    "endMarkerType": 0,
    "fills": [
      {
        "_class": "fill",
        "color": {
          "_class": "color",
          "alpha": 1,
          "blue": 1,
          "green": 1,
          "red": 1
        },
        "contextSettings": {
          "_class": "graphicsContextSettings",
          "blendMode": 0,
          "opacity": 1
        },
        "fillType": 0,
        "gradient": {
          "_class": "gradient",
          "elipseLength": 0,
          "from": "{0.5, 0}",
          "gradientType": 0,
          "stops": [
            {
              "_class": "gradientStop",
              "color": {
                "_class": "color",
                "alpha": 1,
                "blue": 1,
                "green": 1,
                "red": 1
              },
              "position": 0
            },
            {
              "_class": "gradientStop",
              "color": {
                "_class": "color",
                "alpha": 1,
                "blue": 0,
                "green": 0,
                "red": 0
              },
              "position": 1
            }
          ],
          "to": "{0.5, 1}"
        },
        "isEnabled": true,
        "noiseIndex": 0,
        "noiseIntensity": 0,
        "patternFillType": 1,
        "patternTileScale": 1
      }
    ],
    "innerShadows": [
    ],
    "miterLimit": 10,
    "shadows": [
    ],
    "startMarkerType": 0,
    "windingRule": 1
  },
  "symbolID": "EA9EEBCF-0F65-4DD2-99A8-701540F7015D",
  "userInfo": {
    "io.magicsketch.mirror": {
      "highestQuality": 1
    }
  },
  "verticalRulerData": {
    "_class": "rulerData",
    "base": 0,
    "guides": [
    ]
  }
}