{
  "_class": "symbolInstance",
  "booleanOperation": 0,
  "clippingMaskMode": 0,
  "do_objectID": "C507414D-3BF8-48B3-AB3C-E81993235D98",
  "exportOptions": {
    "_class": "exportOptions",
    "exportFormats": [
    ],
    "includedLayerIds": [
    ],
    "layerOptions": 0,
    "shouldTrim": false
  },
  "frame": {
    "_class": "rect",
    "constrainProportions": false,
    "height": 32,
    "width": 92,
    "x": 92,
    "y": 0
  },
  "hasClippingMask": false,
  "horizontalSpacing": 0,
  "isFixedToViewport": false,
  "isFlippedHorizontal": false,
  "isFlippedVertical": false,
  "isLocked": false,
  "isVisible": true,
  "layerListExpandedType": 0,
  "name": "CHIP 2",
  "nameIsFixed": true,
  "overrideValues": [
    {
      "_class": "overrideValue",
      "overrideName": "DCE824D7-CBC7-4E8B-96D0-8CB50FB2571E_symbolID",
      "value": ""
    },
    {
      "_class": "overrideValue",
      "overrideName": "F1EB8AF9-12DE-4E9A-BA21-FA2C5373A6AD_symbolID",
      "value": ""
    },
    {
      "_class": "overrideValue",
      "overrideName": "A257100E-EF9B-4F60-9AF0-DC22C2592A97/C1228624-E91A-4E20-9019-7BFBBAA7A4CF_stringValue",
      "value": "6:30 PM"
    },
    {
      "_class": "overrideValue",
      "overrideName": "A257100E-EF9B-4F60-9AF0-DC22C2592A97/0533900C-A100-49B9-941E-F021909AB6F0_stringValue",
      "value": "Activated"
    },
    {
      "_class": "overrideValue",
      "overrideName": "A257100E-EF9B-4F60-9AF0-DC22C2592A97/503B25E9-F00A-4BE8-B233-A8E646D7810F_stringValue",
      "value": "Active"
    }
  ],
  "resizingConstraint": 63,
  "resizingType": 0,
  "rotation": 0,
  "scale": 1,
  "shouldBreakMaskChain": false,
  "style": {
    "_class": "style",
    "blur": {
      "_class": "blur",
      "center": "{0.5, 0.5}",
      "isEnabled": false,
      "motionAngle": 0,
      "radius": 10,
      "saturation": 1,
      "type": 0
    },
    "borderOptions": {
      "_class": "borderOptions",
      "dashPattern": [
      ],
      "isEnabled": true,
      "lineCapStyle": 0,
      "lineJoinStyle": 0
    },
    "borders": [
    ],
    "colorControls": {
      "_class": "colorControls",
      "brightness": 0,
      "contrast": 1,
      "hue": 0,
      "isEnabled": false,
      "saturation": 1
    },
    "contextSettings": {
      "_class": "graphicsContextSettings",
      "blendMode": 0,
      "opacity": 1
    },
    "do_objectID": "D8D1E353-D241-448D-939D-788638563510",
    "endMarkerType": 0,
    "fills": [
    ],
    "innerShadows": [
    ],
    "miterLimit": 10,
    "shadows": [
    ],
    "startMarkerType": 0,
    "windingRule": 1
  },
  "symbolID": "8D74C262-5B13-4F54-9649-04219874456C",
  "verticalSpacing": 0
}